sofaman/__init__.py
sofaman/sofa.py
sofaman/sofamangen.py
sofaman/generator/generator.py
sofaman/generator/plantuml.py
sofaman/generator/uml2.py
sofaman/ir/ir.py
sofaman/ir/model.py
sofaman/parser/sofa_parser.py
sofaman/parser/grammar/sofa.lark
sofaman/tools/export/id_export.py
sofaman-0.1.7.dist-info/METADATA
sofaman-0.1.7.dist-info/WHEEL
sofaman-0.1.7.dist-info/entry_points.txt
sofaman-0.1.7.dist-info/licenses/LICENSE
sofaman-0.1.7.dist-info/RECORD
