Metadata-Version: 2.4
Name: sofaman
Version: 0.1.7
Summary: Model your architecture in an easy to understand language inspired by Yaml, and generate XMI (UML2) and PlantUML outputs.
Project-URL: Homepage, https://github.com/ivellapillil/sofaman
Project-URL: Issues, https://github.com/ivellapillil/sofaman/issues
Author: Indukumar Vellapillil-Hari
License-Expression: MIT
License-File: LICENSE
Classifier: Operating System :: OS Independent
Classifier: Programming Language :: Python :: 3
Requires-Python: >=3.12
Requires-Dist: click
Requires-Dist: jsonpickle
Requires-Dist: lark>=1.2
Requires-Dist: lxml
Requires-Dist: session-info<2,>=1.0.0
